data/__init__.py
data/anthropic.json
data/cohere.json
data/gemini.json
data/google.json
data/openai.json
data/tools.yaml
abcs/anthropic.py
abcs/cohere.py
abcs/google_gemini.py
abcs/google_vertexai.py
abcs/groq.py
abcs/llm.py
abcs/models.py
abcs/ollama.py
abcs/openai.py
abcs/perplexity.py
abcs/tool_models.py
abcs/tools.py
agents/ada.py
agents/agent.py
agents/aristotle.py
agents/base.py
agents/csv.py
agents/descartes.py
agents/engineer_coordinator.py
agents/engineer_frontend.py
agents/engineer_golang.py
agents/engineer_prompt.py
agents/engineer_python.py
agents/engineer_reviewer.py
agents/engineer_terraform.py
agents/legal.py
agents/news.py
agents/planner.py
agents/plato.py
agents/prompts/ada.md
agents/prompts/csv.md
agents/prompts/engineers/coordinator.md
agents/prompts/engineers/frontend.md
agents/prompts/engineers/golang.md
agents/prompts/engineers/prompt.md
agents/prompts/engineers/python.md
agents/prompts/engineers/reviewer.md
agents/prompts/engineers/terraform.md
agents/prompts/legal.md
agents/prompts/news.md
agents/prompts/people/aristotle.md
agents/prompts/people/descartes.md
agents/prompts/people/plato.md
agents/prompts/people/sun-tzu.md
agents/prompts/planner.md
agents/prompts/stocks.md
agents/prompts/weather.md
agents/stocks.py
agents/sun_tzu.py
agents/utils.py
agents/weather.py
storage/memory_storage.py
storage/storage_manager.py
tools/ada_cli.py
tools/csv.py
tools/files.py
tools/location.py
tools/neo4j.py
tools/news.py
tools/npm.py
tools/stocks.py
tools/tool_manager.py
tools/weather.py
ada_python-0.5.0.dist-info/LICENSE
ada_python-0.5.0.dist-info/METADATA
ada_python-0.5.0.dist-info/WHEEL
ada_python-0.5.0.dist-info/RECORD
